README.md
setup.cfg
setup.py
emailValidation/ValidatePass.py
emailValidation/__init__.py
emailValidation/emailValidation.py
emailValidation.egg-info/PKG-INFO
emailValidation.egg-info/SOURCES.txt
emailValidation.egg-info/dependency_links.txt
emailValidation.egg-info/requires.txt
emailValidation.egg-info/top_level.txt