Metadata-Version: 1.1
Name: emailValidation
Version: 1.0
Summary: To Verify email
Home-page: https://github.com/UmadeviJ/emailValidation.git
Author: uma
Author-email: uma.omnn@gmail.com
License: MIT
Download-URL: https://github.com/UmadeviJ/emailValidation/archive/1.0.tar.gz
Platform: UNKNOWN
